{"sections":[],"schemaVersion":{"minor":3,"patch":0,"major":0},"primaryContentSections":[{"kind":"declarations","declarations":[{"tokens":[{"kind":"keyword","text":"class"},{"kind":"text","text":" "},{"kind":"identifier","text":"InteractiveService"}],"languages":["swift"],"platforms":["macOS"]}]},{"kind":"content","content":[{"anchor":"overview","type":"heading","text":"Overview","level":2},{"type":"paragraph","inlineContent":[{"text":"This class provides an interactive flow for deposits and withdrawals where the anchor service","type":"text"},{"text":" ","type":"text"},{"text":"requires user interaction through a web interface. The user completes KYC and other requirements","type":"text"},{"text":" ","type":"text"},{"text":"in the anchor’s hosted web application, then the anchor handles the on\/off-ramp process.","type":"text"}]},{"type":"paragraph","inlineContent":[{"type":"text","text":"SEP-0024 enables a standardized way for wallets to integrate with anchor services for fiat on\/off-ramps."},{"type":"text","text":" "},{"type":"text","text":"The anchor hosts a web interface where users can provide additional information like KYC data,"},{"type":"text","text":" "},{"type":"text","text":"bank account details, or complete email verification."}]},{"anchor":"Typical-Workflow","type":"heading","text":"Typical Workflow","level":2},{"items":[{"content":[{"type":"paragraph","inlineContent":[{"type":"strong","inlineContent":[{"text":"Initialize Service","type":"text"}]},{"type":"text","text":": Create InteractiveService from anchor’s domain"}]}]},{"content":[{"type":"paragraph","inlineContent":[{"type":"strong","inlineContent":[{"text":"Check Capabilities","type":"text"}]},{"type":"text","text":": Query \/info endpoint to see supported assets and features"}]}]},{"content":[{"inlineContent":[{"type":"strong","inlineContent":[{"type":"text","text":"Authenticate"}]},{"type":"text","text":": Obtain JWT token using SEP-0010 WebAuthenticator"}],"type":"paragraph"}]},{"content":[{"inlineContent":[{"inlineContent":[{"text":"Initiate Flow","type":"text"}],"type":"strong"},{"text":": Start deposit or withdraw, receive interactive URL","type":"text"}],"type":"paragraph"}]},{"content":[{"inlineContent":[{"type":"strong","inlineContent":[{"text":"User Interaction","type":"text"}]},{"type":"text","text":": Open URL in webview\/browser for user to complete requirements"}],"type":"paragraph"}]},{"content":[{"type":"paragraph","inlineContent":[{"type":"strong","inlineContent":[{"text":"Monitor Status","type":"text"}]},{"type":"text","text":": Poll transaction endpoint to track progress"}]}]}],"type":"orderedList"},{"anchor":"Example-Complete-Deposit-Flow","type":"heading","text":"Example: Complete Deposit Flow","level":2},{"code":["\/\/ Step 1: Initialize service from domain","let serviceResult = await InteractiveService.forDomain(","    domain: \"https:\/\/testanchor.stellar.org\"",")","","guard case .success(let service) = serviceResult else { return }","","\/\/ Step 2: Check what assets are supported","let infoResult = await service.info()","guard case .success(let info) = infoResult else { return }","print(\"Supported assets: \\(info.deposit.keys)\")","","\/\/ Step 3: Get JWT token (using SEP-0010)","let jwtToken = \"...\" \/\/ Obtained from WebAuthenticator","","\/\/ Step 4: Initiate deposit","let depositRequest = Sep24DepositRequest(","    assetCode: \"USDC\",","    account: userAccountId,","    jwt: jwtToken",")","let depositResult = await service.deposit(request: depositRequest)","","switch depositResult {","case .success(let response):","    \/\/ Step 5: Open interactive URL in webview","    print(\"Open this URL: \\(response.url)\")","    \/\/ User completes KYC and provides deposit information","","    \/\/ Step 6: Monitor transaction status","    let txRequest = Sep24TransactionRequest(","        id: response.id,","        jwt: jwtToken","    )","    let statusResult = await service.getTransaction(request: txRequest)","    \/\/ Check response.transaction.status","case .failure(let error):","    print(\"Deposit initiation failed: \\(error)\")","}"],"type":"codeListing","syntax":"swift"},{"anchor":"Example-Withdraw-Flow","type":"heading","text":"Example: Withdraw Flow","level":2},{"code":["let withdrawRequest = Sep24WithdrawRequest(","    assetCode: \"USDC\",","    dest: \"bank_account\",","    account: userAccountId,","    jwt: jwtToken",")","","let result = await service.withdraw(request: withdrawRequest)","switch result {","case .success(let response):","    \/\/ Open interactive URL","    print(\"Complete withdraw at: \\(response.url)\")","","    \/\/ User provides bank details and completes verification","    \/\/ Then sends USDC to the anchor's account","case .failure(let error):","    print(\"Withdraw failed: \\(error)\")","}"],"type":"codeListing","syntax":"swift"},{"anchor":"Transaction-Status-Monitoring","type":"heading","text":"Transaction Status Monitoring","level":2},{"code":["\/\/ Poll for transaction status updates","let txRequest = Sep24TransactionRequest(","    id: transactionId,","    jwt: jwtToken",")","","let result = await service.getTransaction(request: txRequest)","if case .success(let response) = result {","    switch response.transaction.status {","    case \"incomplete\":","        \/\/ User needs to complete interactive flow","    case \"pending_user_transfer_start\":","        \/\/ Waiting for user to send funds","    case \"pending_anchor\":","        \/\/ Anchor is processing","    case \"completed\":","        \/\/ Transaction complete","    case \"error\":","        \/\/ Transaction failed","    default:","        break","    }","}"],"type":"codeListing","syntax":"swift"},{"anchor":"Fee-Information","type":"heading","text":"Fee Information","level":2},{"code":["let feeRequest = Sep24FeeRequest(","    operation: \"deposit\",","    assetCode: \"USDC\",","    amount: \"100\",","    jwt: jwtToken",")","","let feeResult = await service.fee(request: feeRequest)","if case .success(let feeResponse) = feeResult {","    print(\"Fee: \\(feeResponse.fee)\")","}"],"type":"codeListing","syntax":"swift"},{"anchor":"Error-Handling","type":"heading","text":"Error Handling","level":2},{"code":["let result = await service.deposit(request: depositRequest)","switch result {","case .success(let response):","    \/\/ Handle success","case .failure(let error):","    switch error {","    case .authenticationRequired:","        \/\/ JWT token missing or expired, re-authenticate with SEP-10","    case .anchorError(let message):","        \/\/ Anchor-specific error (e.g., unsupported asset, amount too large)","    case .parsingResponseFailed(let message):","        \/\/ Response parsing error","    case .horizonError(let horizonError):","        \/\/ Network or HTTP error","    }","}"],"type":"codeListing","syntax":"swift"},{"anchor":"Integration-with-Other-SEPs","type":"heading","text":"Integration with Other SEPs","level":2},{"type":"paragraph","inlineContent":[{"text":"SEP-0024 often works together with:","type":"text"}]},{"items":[{"content":[{"inlineContent":[{"inlineContent":[{"text":"SEP-0010","type":"text"}],"type":"strong"},{"type":"text","text":": Required for authentication (JWT tokens)"}],"type":"paragraph"}]},{"content":[{"inlineContent":[{"inlineContent":[{"text":"SEP-0012","type":"text"}],"type":"strong"},{"text":": For standalone KYC (may be handled in interactive flow)","type":"text"}],"type":"paragraph"}]},{"content":[{"type":"paragraph","inlineContent":[{"inlineContent":[{"text":"SEP-0038","type":"text"}],"type":"strong"},{"text":": For cross-asset swaps during deposit\/withdraw","type":"text"}]}]}],"type":"unorderedList"},{"anchor":"Security-Considerations","type":"heading","text":"Security Considerations","level":2},{"items":[{"content":[{"type":"paragraph","inlineContent":[{"text":"Always use HTTPS for production","type":"text"}]}]},{"content":[{"inlineContent":[{"text":"Validate JWT tokens are current","type":"text"}],"type":"paragraph"}]},{"content":[{"inlineContent":[{"text":"Open interactive URLs in a secure webview","type":"text"}],"type":"paragraph"}]},{"content":[{"inlineContent":[{"text":"Monitor transaction status to detect issues","type":"text"}],"type":"paragraph"}]},{"content":[{"type":"paragraph","inlineContent":[{"text":"Handle user cancellations gracefully","type":"text"}]}]}],"type":"unorderedList"},{"type":"paragraph","inlineContent":[{"type":"text","text":"See also:"}]},{"items":[{"content":[{"type":"paragraph","inlineContent":[{"isActive":true,"type":"reference","identifier":"https:\/\/github.com\/stellar\/stellar-protocol\/blob\/master\/ecosystem\/sep-0024.md"}]}]},{"content":[{"type":"paragraph","inlineContent":[{"type":"text","text":"[WebAuthenticator] for SEP-0010 authentication"}]}]},{"content":[{"inlineContent":[{"type":"text","text":"[StellarToml] for service discovery"}],"type":"paragraph"}]}],"type":"unorderedList"}]}],"kind":"symbol","variants":[{"traits":[{"interfaceLanguage":"swift"}],"paths":["\/documentation\/stellarsdk\/interactiveservice"]}],"metadata":{"symbolKind":"class","modules":[{"name":"stellarsdk"}],"externalID":"c:@M@stellarsdk@objc(cs)InteractiveService","roleHeading":"Class","navigatorTitle":[{"text":"InteractiveService","kind":"identifier"}],"title":"InteractiveService","fragments":[{"text":"class","kind":"keyword"},{"text":" ","kind":"text"},{"text":"InteractiveService","kind":"identifier"}],"role":"symbol"},"identifier":{"url":"doc:\/\/stellar-ios-mac-sdk.stellarsdk\/documentation\/stellarsdk\/InteractiveService","interfaceLanguage":"swift"},"hierarchy":{"paths":[["doc:\/\/stellar-ios-mac-sdk.stellarsdk\/documentation\/stellarsdk"]]},"topicSections":[{"anchor":"Initializers","title":"Initializers","identifiers":["doc:\/\/stellar-ios-mac-sdk.stellarsdk\/documentation\/stellarsdk\/InteractiveService\/init(serviceAddress:)"],"generated":true},{"anchor":"Instance-Properties","title":"Instance Properties","identifiers":["doc:\/\/stellar-ios-mac-sdk.stellarsdk\/documentation\/stellarsdk\/InteractiveService\/serviceAddress"],"generated":true},{"anchor":"Instance-Methods","title":"Instance Methods","identifiers":["doc:\/\/stellar-ios-mac-sdk.stellarsdk\/documentation\/stellarsdk\/InteractiveService\/deposit(request:)","doc:\/\/stellar-ios-mac-sdk.stellarsdk\/documentation\/stellarsdk\/InteractiveService\/deposit(request:completion:)","doc:\/\/stellar-ios-mac-sdk.stellarsdk\/documentation\/stellarsdk\/InteractiveService\/fee(request:)","doc:\/\/stellar-ios-mac-sdk.stellarsdk\/documentation\/stellarsdk\/InteractiveService\/fee(request:completion:)","doc:\/\/stellar-ios-mac-sdk.stellarsdk\/documentation\/stellarsdk\/InteractiveService\/getTransaction(request:)","doc:\/\/stellar-ios-mac-sdk.stellarsdk\/documentation\/stellarsdk\/InteractiveService\/getTransaction(request:completion:)","doc:\/\/stellar-ios-mac-sdk.stellarsdk\/documentation\/stellarsdk\/InteractiveService\/getTransactions(request:)","doc:\/\/stellar-ios-mac-sdk.stellarsdk\/documentation\/stellarsdk\/InteractiveService\/getTransactions(request:completion:)","doc:\/\/stellar-ios-mac-sdk.stellarsdk\/documentation\/stellarsdk\/InteractiveService\/info(language:)","doc:\/\/stellar-ios-mac-sdk.stellarsdk\/documentation\/stellarsdk\/InteractiveService\/info(language:completion:)","doc:\/\/stellar-ios-mac-sdk.stellarsdk\/documentation\/stellarsdk\/InteractiveService\/withdraw(request:)","doc:\/\/stellar-ios-mac-sdk.stellarsdk\/documentation\/stellarsdk\/InteractiveService\/withdraw(request:completion:)"],"generated":true},{"anchor":"Type-Methods","title":"Type Methods","identifiers":["doc:\/\/stellar-ios-mac-sdk.stellarsdk\/documentation\/stellarsdk\/InteractiveService\/forDomain(domain:)","doc:\/\/stellar-ios-mac-sdk.stellarsdk\/documentation\/stellarsdk\/InteractiveService\/forDomain(domain:completion:)"],"generated":true}],"abstract":[{"type":"text","text":"Implements SEP-0024 - Hosted Deposit and Withdrawal."}],"relationshipsSections":[{"type":"inheritsFrom","kind":"relationships","title":"Inherits From","identifiers":["doc:\/\/stellar-ios-mac-sdk.stellarsdk\/objc(cs)NSObject"]},{"type":"conformsTo","kind":"relationships","title":"Conforms To","identifiers":["doc:\/\/stellar-ios-mac-sdk.stellarsdk\/objc(pl)NSObject","doc:\/\/stellar-ios-mac-sdk.stellarsdk\/s7CVarArgP","doc:\/\/stellar-ios-mac-sdk.stellarsdk\/s28CustomDebugStringConvertibleP","doc:\/\/stellar-ios-mac-sdk.stellarsdk\/s23CustomStringConvertibleP","doc:\/\/stellar-ios-mac-sdk.stellarsdk\/SQ","doc:\/\/stellar-ios-mac-sdk.stellarsdk\/SH"]}],"references":{"doc://stellar-ios-mac-sdk.stellarsdk/documentation/stellarsdk/InteractiveService/forDomain(domain:completion:)":{"url":"\/documentation\/stellarsdk\/interactiveservice\/fordomain(domain:completion:)","title":"forDomain(domain:completion:)","abstract":[{"text":"Creates an InteractiveService instance based on information from the stellar.toml file for a given domain.","type":"text"}],"identifier":"doc:\/\/stellar-ios-mac-sdk.stellarsdk\/documentation\/stellarsdk\/InteractiveService\/forDomain(domain:completion:)","kind":"symbol","type":"topic","role":"symbol","fragments":[{"text":"static","kind":"keyword"},{"text":" ","kind":"text"},{"text":"func","kind":"keyword"},{"text":" ","kind":"text"},{"text":"forDomain","kind":"identifier"},{"text":"(","kind":"text"},{"text":"domain","kind":"externalParam"},{"text":": ","kind":"text"},{"preciseIdentifier":"s:SS","text":"String","kind":"typeIdentifier"},{"text":", ","kind":"text"},{"text":"completion","kind":"externalParam"},{"text":": ","kind":"text"},{"preciseIdentifier":"s:10stellarsdk25InteractiveServiceClosurea","text":"InteractiveServiceClosure","kind":"typeIdentifier"},{"text":")","kind":"text"}]},"doc://stellar-ios-mac-sdk.stellarsdk/documentation/stellarsdk/InteractiveService/getTransactions(request:completion:)":{"identifier":"doc:\/\/stellar-ios-mac-sdk.stellarsdk\/documentation\/stellarsdk\/InteractiveService\/getTransactions(request:completion:)","type":"topic","abstract":[],"url":"\/documentation\/stellarsdk\/interactiveservice\/gettransactions(request:completion:)","role":"symbol","fragments":[{"text":"func","kind":"keyword"},{"text":" ","kind":"text"},{"text":"getTransactions","kind":"identifier"},{"text":"(","kind":"text"},{"text":"request","kind":"externalParam"},{"text":": ","kind":"text"},{"text":"Sep24TransactionsRequest","preciseIdentifier":"s:10stellarsdk24Sep24TransactionsRequestV","kind":"typeIdentifier"},{"text":", ","kind":"text"},{"text":"completion","kind":"externalParam"},{"text":": ","kind":"text"},{"text":"Sep24TransactionsResponseClosure","preciseIdentifier":"s:10stellarsdk32Sep24TransactionsResponseClosurea","kind":"typeIdentifier"},{"text":")","kind":"text"}],"title":"getTransactions(request:completion:)","kind":"symbol"},"doc://stellar-ios-mac-sdk.stellarsdk/documentation/stellarsdk/InteractiveService/forDomain(domain:)":{"identifier":"doc:\/\/stellar-ios-mac-sdk.stellarsdk\/documentation\/stellarsdk\/InteractiveService\/forDomain(domain:)","role":"symbol","url":"\/documentation\/stellarsdk\/interactiveservice\/fordomain(domain:)","fragments":[{"text":"static","kind":"keyword"},{"text":" ","kind":"text"},{"text":"func","kind":"keyword"},{"text":" ","kind":"text"},{"text":"forDomain","kind":"identifier"},{"text":"(","kind":"text"},{"text":"domain","kind":"externalParam"},{"text":": ","kind":"text"},{"text":"String","preciseIdentifier":"s:SS","kind":"typeIdentifier"},{"text":") ","kind":"text"},{"text":"async","kind":"keyword"},{"text":" -> ","kind":"text"},{"text":"InteractiveServiceForDomainEnum","preciseIdentifier":"s:10stellarsdk31InteractiveServiceForDomainEnumO","kind":"typeIdentifier"}],"kind":"symbol","title":"forDomain(domain:)","abstract":[{"text":"Creates an InteractiveService instance based on information from the stellar.toml file for a given domain.","type":"text"}],"type":"topic"},"doc://stellar-ios-mac-sdk.stellarsdk/SH":{"type":"unresolvable","identifier":"doc:\/\/stellar-ios-mac-sdk.stellarsdk\/SH","title":"Swift.Hashable"},"doc://stellar-ios-mac-sdk.stellarsdk/documentation/stellarsdk/InteractiveService/getTransaction(request:completion:)":{"abstract":[],"identifier":"doc:\/\/stellar-ios-mac-sdk.stellarsdk\/documentation\/stellarsdk\/InteractiveService\/getTransaction(request:completion:)","url":"\/documentation\/stellarsdk\/interactiveservice\/gettransaction(request:completion:)","title":"getTransaction(request:completion:)","type":"topic","fragments":[{"text":"func","kind":"keyword"},{"text":" ","kind":"text"},{"text":"getTransaction","kind":"identifier"},{"text":"(","kind":"text"},{"text":"request","kind":"externalParam"},{"text":": ","kind":"text"},{"preciseIdentifier":"s:10stellarsdk23Sep24TransactionRequestV","text":"Sep24TransactionRequest","kind":"typeIdentifier"},{"text":", ","kind":"text"},{"text":"completion","kind":"externalParam"},{"text":": ","kind":"text"},{"preciseIdentifier":"s:10stellarsdk31Sep24TransactionResponseClosurea","text":"Sep24TransactionResponseClosure","kind":"typeIdentifier"},{"text":")","kind":"text"}],"role":"symbol","kind":"symbol"},"doc://stellar-ios-mac-sdk.stellarsdk/documentation/stellarsdk/InteractiveService/init(serviceAddress:)":{"kind":"symbol","title":"init(serviceAddress:)","url":"\/documentation\/stellarsdk\/interactiveservice\/init(serviceaddress:)","fragments":[{"text":"init","kind":"identifier"},{"text":"(","kind":"text"},{"text":"serviceAddress","kind":"externalParam"},{"text":": ","kind":"text"},{"text":"String","preciseIdentifier":"s:SS","kind":"typeIdentifier"},{"text":")","kind":"text"}],"role":"symbol","identifier":"doc:\/\/stellar-ios-mac-sdk.stellarsdk\/documentation\/stellarsdk\/InteractiveService\/init(serviceAddress:)","type":"topic","abstract":[]},"doc://stellar-ios-mac-sdk.stellarsdk/s23CustomStringConvertibleP":{"identifier":"doc:\/\/stellar-ios-mac-sdk.stellarsdk\/s23CustomStringConvertibleP","title":"Swift.CustomStringConvertible","type":"unresolvable"},"doc://stellar-ios-mac-sdk.stellarsdk/documentation/stellarsdk/InteractiveService/deposit(request:)":{"fragments":[{"text":"func","kind":"keyword"},{"text":" ","kind":"text"},{"text":"deposit","kind":"identifier"},{"text":"(","kind":"text"},{"text":"request","kind":"externalParam"},{"text":": ","kind":"text"},{"text":"Sep24DepositRequest","preciseIdentifier":"s:10stellarsdk19Sep24DepositRequestV","kind":"typeIdentifier"},{"text":") ","kind":"text"},{"text":"async","kind":"keyword"},{"text":" -> ","kind":"text"},{"text":"Sep24InteractiveResponseEnum","preciseIdentifier":"s:10stellarsdk28Sep24InteractiveResponseEnumO","kind":"typeIdentifier"}],"identifier":"doc:\/\/stellar-ios-mac-sdk.stellarsdk\/documentation\/stellarsdk\/InteractiveService\/deposit(request:)","role":"symbol","abstract":[],"url":"\/documentation\/stellarsdk\/interactiveservice\/deposit(request:)","kind":"symbol","type":"topic","title":"deposit(request:)"},"doc://stellar-ios-mac-sdk.stellarsdk/s28CustomDebugStringConvertibleP":{"identifier":"doc:\/\/stellar-ios-mac-sdk.stellarsdk\/s28CustomDebugStringConvertibleP","title":"Swift.CustomDebugStringConvertible","type":"unresolvable"},"doc://stellar-ios-mac-sdk.stellarsdk/documentation/stellarsdk/InteractiveService/withdraw(request:completion:)":{"url":"\/documentation\/stellarsdk\/interactiveservice\/withdraw(request:completion:)","kind":"symbol","type":"topic","title":"withdraw(request:completion:)","abstract":[],"role":"symbol","fragments":[{"text":"func","kind":"keyword"},{"text":" ","kind":"text"},{"text":"withdraw","kind":"identifier"},{"text":"(","kind":"text"},{"text":"request","kind":"externalParam"},{"text":": ","kind":"text"},{"text":"Sep24WithdrawRequest","preciseIdentifier":"s:10stellarsdk20Sep24WithdrawRequestV","kind":"typeIdentifier"},{"text":", ","kind":"text"},{"text":"completion","kind":"externalParam"},{"text":": ","kind":"text"},{"text":"Sep24InteractiveResponseClosure","preciseIdentifier":"s:10stellarsdk31Sep24InteractiveResponseClosurea","kind":"typeIdentifier"},{"text":")","kind":"text"}],"identifier":"doc:\/\/stellar-ios-mac-sdk.stellarsdk\/documentation\/stellarsdk\/InteractiveService\/withdraw(request:completion:)"},"doc://stellar-ios-mac-sdk.stellarsdk/documentation/stellarsdk/InteractiveService/serviceAddress":{"identifier":"doc:\/\/stellar-ios-mac-sdk.stellarsdk\/documentation\/stellarsdk\/InteractiveService\/serviceAddress","kind":"symbol","title":"serviceAddress","url":"\/documentation\/stellarsdk\/interactiveservice\/serviceaddress","role":"symbol","fragments":[{"text":"var","kind":"keyword"},{"text":" ","kind":"text"},{"text":"serviceAddress","kind":"identifier"},{"text":": ","kind":"text"},{"preciseIdentifier":"s:SS","text":"String","kind":"typeIdentifier"}],"abstract":[],"type":"topic"},"doc://stellar-ios-mac-sdk.stellarsdk/documentation/stellarsdk/InteractiveService/getTransaction(request:)":{"identifier":"doc:\/\/stellar-ios-mac-sdk.stellarsdk\/documentation\/stellarsdk\/InteractiveService\/getTransaction(request:)","fragments":[{"text":"func","kind":"keyword"},{"text":" ","kind":"text"},{"text":"getTransaction","kind":"identifier"},{"text":"(","kind":"text"},{"text":"request","kind":"externalParam"},{"text":": ","kind":"text"},{"text":"Sep24TransactionRequest","preciseIdentifier":"s:10stellarsdk23Sep24TransactionRequestV","kind":"typeIdentifier"},{"text":") ","kind":"text"},{"text":"async","kind":"keyword"},{"text":" -> ","kind":"text"},{"text":"Sep24TransactionResponseEnum","preciseIdentifier":"s:10stellarsdk28Sep24TransactionResponseEnumO","kind":"typeIdentifier"}],"title":"getTransaction(request:)","type":"topic","role":"symbol","abstract":[],"url":"\/documentation\/stellarsdk\/interactiveservice\/gettransaction(request:)","kind":"symbol"},"doc://stellar-ios-mac-sdk.stellarsdk/documentation/stellarsdk/InteractiveService/fee(request:)":{"identifier":"doc:\/\/stellar-ios-mac-sdk.stellarsdk\/documentation\/stellarsdk\/InteractiveService\/fee(request:)","type":"topic","url":"\/documentation\/stellarsdk\/interactiveservice\/fee(request:)","fragments":[{"text":"func","kind":"keyword"},{"text":" ","kind":"text"},{"text":"fee","kind":"identifier"},{"text":"(","kind":"text"},{"text":"request","kind":"externalParam"},{"text":": ","kind":"text"},{"text":"Sep24FeeRequest","kind":"typeIdentifier","preciseIdentifier":"s:10stellarsdk15Sep24FeeRequestV"},{"text":") ","kind":"text"},{"text":"async","kind":"keyword"},{"text":" -> ","kind":"text"},{"text":"Sep24FeeResponseEnum","kind":"typeIdentifier","preciseIdentifier":"s:10stellarsdk20Sep24FeeResponseEnumO"}],"abstract":[{"type":"text","text":"Get the anchor’s to reported fee that would be charged for a given deposit or withdraw operation."},{"type":"text","text":" "},{"type":"text","text":"This is important to allow an anchor to accurately report fees to a user even when the fee schedule is complex."},{"type":"text","text":" "},{"type":"text","text":"If a fee can be fully expressed with the fee_fixed, fee_percent or fee_minimum fields in the \/info response,"},{"type":"text","text":" "},{"type":"text","text":"then an anchor will not implement this endpoint."}],"title":"fee(request:)","kind":"symbol","role":"symbol"},"doc://stellar-ios-mac-sdk.stellarsdk/SQ":{"identifier":"doc:\/\/stellar-ios-mac-sdk.stellarsdk\/SQ","title":"Swift.Equatable","type":"unresolvable"},"doc://stellar-ios-mac-sdk.stellarsdk/documentation/stellarsdk/InteractiveService/fee(request:completion:)":{"url":"\/documentation\/stellarsdk\/interactiveservice\/fee(request:completion:)","title":"fee(request:completion:)","type":"topic","abstract":[{"type":"text","text":"Get the anchor’s to reported fee that would be charged for a given deposit or withdraw operation."},{"type":"text","text":" "},{"type":"text","text":"This is important to allow an anchor to accurately report fees to a user even when the fee schedule is complex."},{"type":"text","text":" "},{"type":"text","text":"If a fee can be fully expressed with the fee_fixed, fee_percent or fee_minimum fields in the \/info response,"},{"type":"text","text":" "},{"type":"text","text":"then an anchor will not implement this endpoint."}],"kind":"symbol","identifier":"doc:\/\/stellar-ios-mac-sdk.stellarsdk\/documentation\/stellarsdk\/InteractiveService\/fee(request:completion:)","role":"symbol","fragments":[{"text":"func","kind":"keyword"},{"text":" ","kind":"text"},{"text":"fee","kind":"identifier"},{"text":"(","kind":"text"},{"text":"request","kind":"externalParam"},{"text":": ","kind":"text"},{"text":"Sep24FeeRequest","kind":"typeIdentifier","preciseIdentifier":"s:10stellarsdk15Sep24FeeRequestV"},{"text":", ","kind":"text"},{"text":"completion","kind":"externalParam"},{"text":": ","kind":"text"},{"text":"Sep24FeeResponseClosure","kind":"typeIdentifier","preciseIdentifier":"s:10stellarsdk23Sep24FeeResponseClosurea"},{"text":")","kind":"text"}]},"doc://stellar-ios-mac-sdk.stellarsdk/documentation/stellarsdk":{"type":"topic","url":"\/documentation\/stellarsdk","kind":"symbol","role":"collection","identifier":"doc:\/\/stellar-ios-mac-sdk.stellarsdk\/documentation\/stellarsdk","abstract":[],"title":"stellarsdk"},"doc://stellar-ios-mac-sdk.stellarsdk/documentation/stellarsdk/InteractiveService/info(language:)":{"identifier":"doc:\/\/stellar-ios-mac-sdk.stellarsdk\/documentation\/stellarsdk\/InteractiveService\/info(language:)","type":"topic","role":"symbol","abstract":[{"type":"text","text":"Get the anchors basic info about what their TRANSFER_SERVER_SEP0024 support to wallets and clients."}],"kind":"symbol","title":"info(language:)","fragments":[{"text":"func","kind":"keyword"},{"text":" ","kind":"text"},{"text":"info","kind":"identifier"},{"text":"(","kind":"text"},{"text":"language","kind":"externalParam"},{"text":": ","kind":"text"},{"text":"String","kind":"typeIdentifier","preciseIdentifier":"s:SS"},{"text":"?) ","kind":"text"},{"text":"async","kind":"keyword"},{"text":" -> ","kind":"text"},{"text":"Sep24InfoResponseEnum","kind":"typeIdentifier","preciseIdentifier":"s:10stellarsdk21Sep24InfoResponseEnumO"}],"url":"\/documentation\/stellarsdk\/interactiveservice\/info(language:)"},"doc://stellar-ios-mac-sdk.stellarsdk/s7CVarArgP":{"type":"unresolvable","identifier":"doc:\/\/stellar-ios-mac-sdk.stellarsdk\/s7CVarArgP","title":"Swift.CVarArg"},"doc://stellar-ios-mac-sdk.stellarsdk/documentation/stellarsdk/InteractiveService/deposit(request:completion:)":{"fragments":[{"text":"func","kind":"keyword"},{"text":" ","kind":"text"},{"text":"deposit","kind":"identifier"},{"text":"(","kind":"text"},{"text":"request","kind":"externalParam"},{"text":": ","kind":"text"},{"preciseIdentifier":"s:10stellarsdk19Sep24DepositRequestV","text":"Sep24DepositRequest","kind":"typeIdentifier"},{"text":", ","kind":"text"},{"text":"completion","kind":"externalParam"},{"text":": ","kind":"text"},{"preciseIdentifier":"s:10stellarsdk31Sep24InteractiveResponseClosurea","text":"Sep24InteractiveResponseClosure","kind":"typeIdentifier"},{"text":")","kind":"text"}],"role":"symbol","identifier":"doc:\/\/stellar-ios-mac-sdk.stellarsdk\/documentation\/stellarsdk\/InteractiveService\/deposit(request:completion:)","url":"\/documentation\/stellarsdk\/interactiveservice\/deposit(request:completion:)","type":"topic","abstract":[],"title":"deposit(request:completion:)","kind":"symbol"},"doc://stellar-ios-mac-sdk.stellarsdk/documentation/stellarsdk/InteractiveService/info(language:completion:)":{"fragments":[{"text":"func","kind":"keyword"},{"text":" ","kind":"text"},{"text":"info","kind":"identifier"},{"text":"(","kind":"text"},{"text":"language","kind":"externalParam"},{"text":": ","kind":"text"},{"text":"String","preciseIdentifier":"s:SS","kind":"typeIdentifier"},{"text":"?, ","kind":"text"},{"text":"completion","kind":"externalParam"},{"text":": ","kind":"text"},{"text":"Sep24InfoResponseClosure","preciseIdentifier":"s:10stellarsdk24Sep24InfoResponseClosurea","kind":"typeIdentifier"},{"text":")","kind":"text"}],"abstract":[{"text":"Get the anchors basic info about what their TRANSFER_SERVER_SEP0024 support to wallets and clients.","type":"text"}],"kind":"symbol","role":"symbol","type":"topic","identifier":"doc:\/\/stellar-ios-mac-sdk.stellarsdk\/documentation\/stellarsdk\/InteractiveService\/info(language:completion:)","title":"info(language:completion:)","url":"\/documentation\/stellarsdk\/interactiveservice\/info(language:completion:)"},"doc://stellar-ios-mac-sdk.stellarsdk/documentation/stellarsdk/InteractiveService/getTransactions(request:)":{"abstract":[],"identifier":"doc:\/\/stellar-ios-mac-sdk.stellarsdk\/documentation\/stellarsdk\/InteractiveService\/getTransactions(request:)","role":"symbol","kind":"symbol","url":"\/documentation\/stellarsdk\/interactiveservice\/gettransactions(request:)","title":"getTransactions(request:)","type":"topic","fragments":[{"text":"func","kind":"keyword"},{"text":" ","kind":"text"},{"text":"getTransactions","kind":"identifier"},{"text":"(","kind":"text"},{"text":"request","kind":"externalParam"},{"text":": ","kind":"text"},{"preciseIdentifier":"s:10stellarsdk24Sep24TransactionsRequestV","text":"Sep24TransactionsRequest","kind":"typeIdentifier"},{"text":") ","kind":"text"},{"text":"async","kind":"keyword"},{"text":" -> ","kind":"text"},{"preciseIdentifier":"s:10stellarsdk29Sep24TransactionsResponseEnumO","text":"Sep24TransactionsResponseEnum","kind":"typeIdentifier"}]},"doc://stellar-ios-mac-sdk.stellarsdk/documentation/stellarsdk/InteractiveService":{"navigatorTitle":[{"text":"InteractiveService","kind":"identifier"}],"type":"topic","identifier":"doc:\/\/stellar-ios-mac-sdk.stellarsdk\/documentation\/stellarsdk\/InteractiveService","abstract":[{"type":"text","text":"Implements SEP-0024 - Hosted Deposit and Withdrawal."}],"title":"InteractiveService","kind":"symbol","url":"\/documentation\/stellarsdk\/interactiveservice","role":"symbol","fragments":[{"text":"class","kind":"keyword"},{"text":" ","kind":"text"},{"text":"InteractiveService","kind":"identifier"}]},"doc://stellar-ios-mac-sdk.stellarsdk/documentation/stellarsdk/InteractiveService/withdraw(request:)":{"abstract":[],"title":"withdraw(request:)","url":"\/documentation\/stellarsdk\/interactiveservice\/withdraw(request:)","fragments":[{"text":"func","kind":"keyword"},{"text":" ","kind":"text"},{"text":"withdraw","kind":"identifier"},{"text":"(","kind":"text"},{"text":"request","kind":"externalParam"},{"text":": ","kind":"text"},{"text":"Sep24WithdrawRequest","kind":"typeIdentifier","preciseIdentifier":"s:10stellarsdk20Sep24WithdrawRequestV"},{"kind":"text","text":") "},{"kind":"keyword","text":"async"},{"kind":"text","text":" -> "},{"kind":"typeIdentifier","preciseIdentifier":"s:10stellarsdk28Sep24InteractiveResponseEnumO","text":"Sep24InteractiveResponseEnum"}],"type":"topic","kind":"symbol","identifier":"doc:\/\/stellar-ios-mac-sdk.stellarsdk\/documentation\/stellarsdk\/InteractiveService\/withdraw(request:)","role":"symbol"},"doc://stellar-ios-mac-sdk.stellarsdk/objc(pl)NSObject":{"type":"unresolvable","identifier":"doc:\/\/stellar-ios-mac-sdk.stellarsdk\/objc(pl)NSObject","title":"ObjectiveC.NSObjectProtocol"},"https://github.com/stellar/stellar-protocol/blob/master/ecosystem/sep-0024.md":{"identifier":"https:\/\/github.com\/stellar\/stellar-protocol\/blob\/master\/ecosystem\/sep-0024.md","title":"SEP-0024 Specification","titleInlineContent":[{"text":"SEP-0024 Specification","type":"text"}],"url":"https:\/\/github.com\/stellar\/stellar-protocol\/blob\/master\/ecosystem\/sep-0024.md","type":"link"},"doc://stellar-ios-mac-sdk.stellarsdk/objc(cs)NSObject":{"type":"unresolvable","identifier":"doc:\/\/stellar-ios-mac-sdk.stellarsdk\/objc(cs)NSObject","title":"ObjectiveC.NSObject"}}}