{"abstract":[{"type":"text","text":"Implementation of the W3C Server-Sent Events (SSE) protocol for streaming data from Horizon."}],"kind":"symbol","primaryContentSections":[{"kind":"declarations","declarations":[{"tokens":[{"kind":"keyword","text":"class"},{"kind":"text","text":" "},{"kind":"identifier","text":"EventSource"}],"platforms":["macOS"],"languages":["swift"]}]},{"kind":"content","content":[{"anchor":"overview","level":2,"type":"heading","text":"Overview"},{"inlineContent":[{"type":"text","text":"This class implements a client for the Server-Sent Events protocol, which enables"},{"type":"text","text":" "},{"type":"text","text":"servers to push real-time updates to clients over HTTP. The implementation is used"},{"type":"text","text":" "},{"type":"text","text":"throughout the SDK to stream live data from Stellar Horizon servers, including"},{"type":"text","text":" "},{"type":"text","text":"ledgers, transactions, operations, effects, and account changes."}],"type":"paragraph"},{"anchor":"Protocol-Overview","level":2,"type":"heading","text":"Protocol Overview"},{"inlineContent":[{"text":"Server-Sent Events provide a unidirectional channel from server to client over HTTP.","type":"text"},{"text":" ","type":"text"},{"text":"The connection remains open, and the server pushes updates as formatted text messages.","type":"text"},{"text":" ","type":"text"},{"text":"Key features include:","type":"text"}],"type":"paragraph"},{"type":"unorderedList","items":[{"content":[{"type":"paragraph","inlineContent":[{"type":"text","text":"Automatic reconnection with configurable retry intervals"}]}]},{"content":[{"type":"paragraph","inlineContent":[{"text":"Event identification for resuming from last received message","type":"text"}]}]},{"content":[{"type":"paragraph","inlineContent":[{"text":"Named events for routing different message types","type":"text"}]}]},{"content":[{"type":"paragraph","inlineContent":[{"type":"text","text":"Long-lived connections with appropriate timeouts"}]}]}]},{"anchor":"Usage-Example","level":2,"type":"heading","text":"Usage Example"},{"code":["\/\/ Stream ledger updates from Horizon","let url = \"https:\/\/horizon.stellar.org\/ledgers?cursor=now\"","let eventSource = EventSource(url: url)","","eventSource.onOpen { response in","    print(\"Connection opened, status: \\(response?.statusCode ?? 0)\")","}","","eventSource.onMessage { id, event, data in","    print(\"Received message - ID: \\(id ?? \"none\"), Event: \\(event ?? \"none\")\")","    \/\/ Parse data as JSON ledger response","    if let ledgerData = data?.data(using: .utf8) {","        \/\/ Process ledger data","    }","}","","eventSource.onError { error in","    print(\"Connection error: \\(error?.localizedDescription ?? \"unknown\")\")","}","","\/\/ Close when done","eventSource.close()"],"type":"codeListing","syntax":"swift"},{"anchor":"Event-Handlers","level":2,"type":"heading","text":"Event Handlers"},{"inlineContent":[{"text":"The EventSource supports three types of callbacks:","type":"text"}],"type":"paragraph"},{"type":"unorderedList","items":[{"content":[{"inlineContent":[{"type":"codeVoice","code":"onOpen"},{"type":"text","text":": Called when connection is established"}],"type":"paragraph"}]},{"content":[{"type":"paragraph","inlineContent":[{"code":"onMessage","type":"codeVoice"},{"type":"text","text":": Called for each message received"}]}]},{"content":[{"type":"paragraph","inlineContent":[{"type":"codeVoice","code":"onError"},{"text":": Called when errors occur","type":"text"}]}]}]},{"inlineContent":[{"type":"text","text":"Additionally, named event listeners can be registered for specific event types:"}],"type":"paragraph"},{"code":["eventSource.addEventListener(\"ledger-update\") { id, event, data in","    \/\/ Handle ledger-specific events","}"],"type":"codeListing","syntax":"swift"},{"level":2,"anchor":"Automatic-Reconnection","type":"heading","text":"Automatic Reconnection"},{"inlineContent":[{"text":"The implementation automatically reconnects on connection failures using an","type":"text"},{"text":" ","type":"text"},{"text":"exponential backoff strategy. The retry interval can be set by the server","type":"text"},{"text":" ","type":"text"},{"text":"using the ","type":"text"},{"type":"codeVoice","code":"retry:"},{"text":" field in the event stream, defaulting to 3000 milliseconds.","type":"text"}],"type":"paragraph"},{"level":2,"anchor":"Last-Event-ID","type":"heading","text":"Last Event ID"},{"inlineContent":[{"type":"text","text":"To support reliable streaming, the last received event ID is persisted and"},{"type":"text","text":" "},{"type":"text","text":"sent with reconnection requests using the "},{"type":"codeVoice","code":"Last-Event-Id"},{"type":"text","text":" header. This allows"},{"type":"text","text":" "},{"type":"text","text":"the server to resume streaming from where it left off."}],"type":"paragraph"},{"inlineContent":[{"type":"text","text":"See also:"}],"type":"paragraph"},{"items":[{"content":[{"type":"paragraph","inlineContent":[{"isActive":true,"type":"reference","identifier":"https:\/\/html.spec.whatwg.org\/multipage\/server-sent-events.html"}]}]},{"content":[{"type":"paragraph","inlineContent":[{"type":"reference","identifier":"https:\/\/developers.stellar.org","isActive":true}]}]},{"content":[{"inlineContent":[{"text":"[StreamingHelper] for simplified Horizon streaming integration","type":"text"}],"type":"paragraph"}]}],"type":"unorderedList"}]}],"topicSections":[{"identifiers":["doc:\/\/stellar-ios-mac-sdk.stellarsdk\/documentation\/stellarsdk\/EventSource\/init(url:headers:)"],"title":"Initializers","anchor":"Initializers","generated":true},{"identifiers":["doc:\/\/stellar-ios-mac-sdk.stellarsdk\/documentation\/stellarsdk\/EventSource\/readyState","doc:\/\/stellar-ios-mac-sdk.stellarsdk\/documentation\/stellarsdk\/EventSource\/retryTime"],"title":"Instance Properties","anchor":"Instance-Properties","generated":true},{"identifiers":["doc:\/\/stellar-ios-mac-sdk.stellarsdk\/documentation\/stellarsdk\/EventSource\/addEventListener(_:handler:)","doc:\/\/stellar-ios-mac-sdk.stellarsdk\/documentation\/stellarsdk\/EventSource\/close()","doc:\/\/stellar-ios-mac-sdk.stellarsdk\/documentation\/stellarsdk\/EventSource\/events()","doc:\/\/stellar-ios-mac-sdk.stellarsdk\/documentation\/stellarsdk\/EventSource\/onError(_:)","doc:\/\/stellar-ios-mac-sdk.stellarsdk\/documentation\/stellarsdk\/EventSource\/onMessage(_:)","doc:\/\/stellar-ios-mac-sdk.stellarsdk\/documentation\/stellarsdk\/EventSource\/onOpen(_:)","doc:\/\/stellar-ios-mac-sdk.stellarsdk\/documentation\/stellarsdk\/EventSource\/removeEventListener(_:)","doc:\/\/stellar-ios-mac-sdk.stellarsdk\/documentation\/stellarsdk\/EventSource\/urlSession(_:dataTask:didReceive:)","doc:\/\/stellar-ios-mac-sdk.stellarsdk\/documentation\/stellarsdk\/EventSource\/urlSession(_:dataTask:didReceive:completionHandler:)","doc:\/\/stellar-ios-mac-sdk.stellarsdk\/documentation\/stellarsdk\/EventSource\/urlSession(_:task:didCompleteWithError:)"],"title":"Instance Methods","anchor":"Instance-Methods","generated":true},{"generated":true,"anchor":"Type-Methods","title":"Type Methods","identifiers":["doc:\/\/stellar-ios-mac-sdk.stellarsdk\/documentation\/stellarsdk\/EventSource\/basicAuth(_:password:)"]}],"hierarchy":{"paths":[["doc:\/\/stellar-ios-mac-sdk.stellarsdk\/documentation\/stellarsdk"]]},"variants":[{"traits":[{"interfaceLanguage":"swift"}],"paths":["\/documentation\/stellarsdk\/eventsource"]}],"sections":[],"schemaVersion":{"minor":3,"patch":0,"major":0},"relationshipsSections":[{"kind":"relationships","title":"Inherits From","type":"inheritsFrom","identifiers":["doc:\/\/stellar-ios-mac-sdk.stellarsdk\/objc(cs)NSObject"]},{"kind":"relationships","title":"Conforms To","type":"conformsTo","identifiers":["doc:\/\/stellar-ios-mac-sdk.stellarsdk\/objc(pl)NSURLSessionDataDelegate","doc:\/\/stellar-ios-mac-sdk.stellarsdk\/objc(pl)NSURLSessionDelegate","doc:\/\/stellar-ios-mac-sdk.stellarsdk\/objc(pl)NSURLSessionTaskDelegate","doc:\/\/stellar-ios-mac-sdk.stellarsdk\/objc(pl)NSObject","doc:\/\/stellar-ios-mac-sdk.stellarsdk\/s7CVarArgP","doc:\/\/stellar-ios-mac-sdk.stellarsdk\/s28CustomDebugStringConvertibleP","doc:\/\/stellar-ios-mac-sdk.stellarsdk\/s23CustomStringConvertibleP","doc:\/\/stellar-ios-mac-sdk.stellarsdk\/SQ","doc:\/\/stellar-ios-mac-sdk.stellarsdk\/SH","doc:\/\/stellar-ios-mac-sdk.stellarsdk\/s8SendableP"]}],"identifier":{"url":"doc:\/\/stellar-ios-mac-sdk.stellarsdk\/documentation\/stellarsdk\/EventSource","interfaceLanguage":"swift"},"metadata":{"modules":[{"name":"stellarsdk"}],"externalID":"c:@M@stellarsdk@objc(cs)EventSource","symbolKind":"class","roleHeading":"Class","role":"symbol","fragments":[{"kind":"keyword","text":"class"},{"kind":"text","text":" "},{"kind":"identifier","text":"EventSource"}],"title":"EventSource","navigatorTitle":[{"text":"EventSource","kind":"identifier"}]},"references":{"doc://stellar-ios-mac-sdk.stellarsdk/objc(pl)NSURLSessionTaskDelegate":{"identifier":"doc:\/\/stellar-ios-mac-sdk.stellarsdk\/objc(pl)NSURLSessionTaskDelegate","title":"Foundation.URLSessionTaskDelegate","type":"unresolvable"},"doc://stellar-ios-mac-sdk.stellarsdk/documentation/stellarsdk/EventSource/init(url:headers:)":{"url":"\/documentation\/stellarsdk\/eventsource\/init(url:headers:)","abstract":[{"type":"text","text":"Creates a new EventSource instance and establishes connection to the specified URL."}],"role":"symbol","title":"init(url:headers:)","fragments":[{"text":"init","kind":"identifier"},{"text":"(","kind":"text"},{"text":"url","kind":"externalParam"},{"text":": ","kind":"text"},{"preciseIdentifier":"s:SS","text":"String","kind":"typeIdentifier"},{"text":", ","kind":"text"},{"text":"headers","kind":"externalParam"},{"text":": [","kind":"text"},{"preciseIdentifier":"s:SS","text":"String","kind":"typeIdentifier"},{"text":" : ","kind":"text"},{"preciseIdentifier":"s:SS","text":"String","kind":"typeIdentifier"},{"text":"])","kind":"text"}],"kind":"symbol","type":"topic","identifier":"doc:\/\/stellar-ios-mac-sdk.stellarsdk\/documentation\/stellarsdk\/EventSource\/init(url:headers:)"},"doc://stellar-ios-mac-sdk.stellarsdk/objc(pl)NSObject":{"identifier":"doc:\/\/stellar-ios-mac-sdk.stellarsdk\/objc(pl)NSObject","title":"ObjectiveC.NSObjectProtocol","type":"unresolvable"},"doc://stellar-ios-mac-sdk.stellarsdk/documentation/stellarsdk/EventSource/urlSession(_:task:didCompleteWithError:)":{"url":"\/documentation\/stellarsdk\/eventsource\/urlsession(_:task:didcompletewitherror:)","title":"urlSession(_:task:didCompleteWithError:)","fragments":[{"text":"func","kind":"keyword"},{"text":" ","kind":"text"},{"text":"urlSession","kind":"identifier"},{"text":"(","kind":"text"},{"preciseIdentifier":"c:objc(cs)NSURLSession","text":"URLSession","kind":"typeIdentifier"},{"text":", ","kind":"text"},{"text":"task","kind":"externalParam"},{"text":": ","kind":"text"},{"preciseIdentifier":"c:objc(cs)NSURLSessionTask","text":"URLSessionTask","kind":"typeIdentifier"},{"text":", ","kind":"text"},{"text":"didCompleteWithError","kind":"externalParam"},{"text":": ","kind":"text"},{"preciseIdentifier":"s:s5ErrorP","text":"Error","kind":"typeIdentifier"},{"text":"?)","kind":"text"}],"abstract":[],"type":"topic","kind":"symbol","identifier":"doc:\/\/stellar-ios-mac-sdk.stellarsdk\/documentation\/stellarsdk\/EventSource\/urlSession(_:task:didCompleteWithError:)","role":"symbol"},"doc://stellar-ios-mac-sdk.stellarsdk/documentation/stellarsdk/EventSource":{"identifier":"doc:\/\/stellar-ios-mac-sdk.stellarsdk\/documentation\/stellarsdk\/EventSource","type":"topic","url":"\/documentation\/stellarsdk\/eventsource","abstract":[{"type":"text","text":"Implementation of the W3C Server-Sent Events (SSE) protocol for streaming data from Horizon."}],"role":"symbol","fragments":[{"text":"class","kind":"keyword"},{"text":" ","kind":"text"},{"text":"EventSource","kind":"identifier"}],"navigatorTitle":[{"text":"EventSource","kind":"identifier"}],"kind":"symbol","title":"EventSource"},"doc://stellar-ios-mac-sdk.stellarsdk/documentation/stellarsdk/EventSource/onMessage(_:)":{"abstract":[{"text":"Registers a callback to be invoked when a message is received.","type":"text"}],"fragments":[{"text":"func","kind":"keyword"},{"text":" ","kind":"text"},{"text":"onMessage","kind":"identifier"},{"text":"(((","kind":"text"},{"text":"_","kind":"externalParam"},{"text":" ","kind":"text"},{"text":"id","kind":"internalParam"},{"text":": ","kind":"text"},{"text":"String","preciseIdentifier":"s:SS","kind":"typeIdentifier"},{"text":"?, ","kind":"text"},{"text":"_","kind":"externalParam"},{"text":" ","kind":"text"},{"text":"event","kind":"internalParam"},{"text":": ","kind":"text"},{"text":"String","preciseIdentifier":"s:SS","kind":"typeIdentifier"},{"text":"?, ","kind":"text"},{"text":"_","kind":"externalParam"},{"text":" ","kind":"text"},{"text":"data","kind":"internalParam"},{"text":": ","kind":"text"},{"text":"String","preciseIdentifier":"s:SS","kind":"typeIdentifier"},{"text":"?) -> ","kind":"text"},{"text":"Void","preciseIdentifier":"s:s4Voida","kind":"typeIdentifier"},{"text":"))","kind":"text"}],"role":"symbol","type":"topic","kind":"symbol","title":"onMessage(_:)","url":"\/documentation\/stellarsdk\/eventsource\/onmessage(_:)","identifier":"doc:\/\/stellar-ios-mac-sdk.stellarsdk\/documentation\/stellarsdk\/EventSource\/onMessage(_:)"},"doc://stellar-ios-mac-sdk.stellarsdk/documentation/stellarsdk/EventSource/removeEventListener(_:)":{"kind":"symbol","fragments":[{"text":"func","kind":"keyword"},{"text":" ","kind":"text"},{"text":"removeEventListener","kind":"identifier"},{"text":"(","kind":"text"},{"text":"String","preciseIdentifier":"s:SS","kind":"typeIdentifier"},{"text":")","kind":"text"}],"role":"symbol","identifier":"doc:\/\/stellar-ios-mac-sdk.stellarsdk\/documentation\/stellarsdk\/EventSource\/removeEventListener(_:)","type":"topic","abstract":[{"type":"text","text":"Removes the handler for a specific event type."}],"title":"removeEventListener(_:)","url":"\/documentation\/stellarsdk\/eventsource\/removeeventlistener(_:)"},"doc://stellar-ios-mac-sdk.stellarsdk/documentation/stellarsdk/EventSource/events()":{"type":"topic","title":"events()","identifier":"doc:\/\/stellar-ios-mac-sdk.stellarsdk\/documentation\/stellarsdk\/EventSource\/events()","abstract":[{"type":"text","text":"Returns an array of all registered event type names."}],"role":"symbol","kind":"symbol","fragments":[{"kind":"keyword","text":"func"},{"kind":"text","text":" "},{"kind":"identifier","text":"events"},{"kind":"text","text":"() -> "},{"kind":"typeIdentifier","preciseIdentifier":"s:Sa","text":"Array"},{"kind":"text","text":"<"},{"kind":"typeIdentifier","preciseIdentifier":"s:SS","text":"String"},{"kind":"text","text":">"}],"url":"\/documentation\/stellarsdk\/eventsource\/events()"},"https://developers.stellar.org":{"titleInlineContent":[{"text":"Stellar developer docs","type":"text"}],"url":"https:\/\/developers.stellar.org","identifier":"https:\/\/developers.stellar.org","title":"Stellar developer docs","type":"link"},"doc://stellar-ios-mac-sdk.stellarsdk/s23CustomStringConvertibleP":{"type":"unresolvable","identifier":"doc:\/\/stellar-ios-mac-sdk.stellarsdk\/s23CustomStringConvertibleP","title":"Swift.CustomStringConvertible"},"doc://stellar-ios-mac-sdk.stellarsdk/s28CustomDebugStringConvertibleP":{"identifier":"doc:\/\/stellar-ios-mac-sdk.stellarsdk\/s28CustomDebugStringConvertibleP","title":"Swift.CustomDebugStringConvertible","type":"unresolvable"},"doc://stellar-ios-mac-sdk.stellarsdk/documentation/stellarsdk/EventSource/onOpen(_:)":{"title":"onOpen(_:)","identifier":"doc:\/\/stellar-ios-mac-sdk.stellarsdk\/documentation\/stellarsdk\/EventSource\/onOpen(_:)","url":"\/documentation\/stellarsdk\/eventsource\/onopen(_:)","role":"symbol","type":"topic","kind":"symbol","abstract":[{"text":"Registers a callback to be invoked when the connection opens.","type":"text"}],"fragments":[{"text":"func","kind":"keyword"},{"text":" ","kind":"text"},{"text":"onOpen","kind":"identifier"},{"text":"(((","kind":"text"},{"preciseIdentifier":"c:objc(cs)NSHTTPURLResponse","text":"HTTPURLResponse","kind":"typeIdentifier"},{"text":"?) -> ","kind":"text"},{"preciseIdentifier":"s:s4Voida","text":"Void","kind":"typeIdentifier"},{"text":"))","kind":"text"}]},"doc://stellar-ios-mac-sdk.stellarsdk/documentation/stellarsdk/EventSource/retryTime":{"fragments":[{"kind":"keyword","text":"var"},{"kind":"text","text":" "},{"kind":"identifier","text":"retryTime"},{"kind":"text","text":": "},{"kind":"typeIdentifier","text":"Int","preciseIdentifier":"s:Si"}],"kind":"symbol","title":"retryTime","role":"symbol","type":"topic","url":"\/documentation\/stellarsdk\/eventsource\/retrytime","abstract":[],"identifier":"doc:\/\/stellar-ios-mac-sdk.stellarsdk\/documentation\/stellarsdk\/EventSource\/retryTime"},"doc://stellar-ios-mac-sdk.stellarsdk/objc(pl)NSURLSessionDataDelegate":{"identifier":"doc:\/\/stellar-ios-mac-sdk.stellarsdk\/objc(pl)NSURLSessionDataDelegate","title":"Foundation.URLSessionDataDelegate","type":"unresolvable"},"doc://stellar-ios-mac-sdk.stellarsdk/s8SendableP":{"identifier":"doc:\/\/stellar-ios-mac-sdk.stellarsdk\/s8SendableP","title":"Swift.Sendable","type":"unresolvable"},"doc://stellar-ios-mac-sdk.stellarsdk/SH":{"identifier":"doc:\/\/stellar-ios-mac-sdk.stellarsdk\/SH","title":"Swift.Hashable","type":"unresolvable"},"doc://stellar-ios-mac-sdk.stellarsdk/documentation/stellarsdk":{"type":"topic","url":"\/documentation\/stellarsdk","kind":"symbol","role":"collection","identifier":"doc:\/\/stellar-ios-mac-sdk.stellarsdk\/documentation\/stellarsdk","abstract":[],"title":"stellarsdk"},"doc://stellar-ios-mac-sdk.stellarsdk/objc(cs)NSObject":{"identifier":"doc:\/\/stellar-ios-mac-sdk.stellarsdk\/objc(cs)NSObject","title":"ObjectiveC.NSObject","type":"unresolvable"},"doc://stellar-ios-mac-sdk.stellarsdk/documentation/stellarsdk/EventSource/onError(_:)":{"identifier":"doc:\/\/stellar-ios-mac-sdk.stellarsdk\/documentation\/stellarsdk\/EventSource\/onError(_:)","abstract":[{"type":"text","text":"Registers a callback to be invoked when an error occurs."}],"title":"onError(_:)","type":"topic","role":"symbol","fragments":[{"kind":"keyword","text":"func"},{"kind":"text","text":" "},{"kind":"identifier","text":"onError"},{"kind":"text","text":"((("},{"kind":"typeIdentifier","text":"NSError","preciseIdentifier":"c:objc(cs)NSError"},{"kind":"text","text":"?) -> "},{"kind":"typeIdentifier","text":"Void","preciseIdentifier":"s:s4Voida"},{"kind":"text","text":"))"}],"url":"\/documentation\/stellarsdk\/eventsource\/onerror(_:)","kind":"symbol"},"doc://stellar-ios-mac-sdk.stellarsdk/documentation/stellarsdk/EventSource/basicAuth(_:password:)":{"url":"\/documentation\/stellarsdk\/eventsource\/basicauth(_:password:)","abstract":[],"kind":"symbol","type":"topic","identifier":"doc:\/\/stellar-ios-mac-sdk.stellarsdk\/documentation\/stellarsdk\/EventSource\/basicAuth(_:password:)","title":"basicAuth(_:password:)","fragments":[{"text":"class","kind":"keyword"},{"text":" ","kind":"text"},{"text":"func","kind":"keyword"},{"text":" ","kind":"text"},{"text":"basicAuth","kind":"identifier"},{"text":"(","kind":"text"},{"text":"String","kind":"typeIdentifier","preciseIdentifier":"s:SS"},{"text":", ","kind":"text"},{"text":"password","kind":"externalParam"},{"text":": ","kind":"text"},{"text":"String","kind":"typeIdentifier","preciseIdentifier":"s:SS"},{"text":") -> ","kind":"text"},{"text":"String","kind":"typeIdentifier","preciseIdentifier":"s:SS"}],"role":"symbol"},"doc://stellar-ios-mac-sdk.stellarsdk/documentation/stellarsdk/EventSource/urlSession(_:dataTask:didReceive:completionHandler:)":{"abstract":[],"title":"urlSession(_:dataTask:didReceive:completionHandler:)","url":"\/documentation\/stellarsdk\/eventsource\/urlsession(_:datatask:didreceive:completionhandler:)","role":"symbol","identifier":"doc:\/\/stellar-ios-mac-sdk.stellarsdk\/documentation\/stellarsdk\/EventSource\/urlSession(_:dataTask:didReceive:completionHandler:)","fragments":[{"kind":"keyword","text":"func"},{"kind":"text","text":" "},{"kind":"identifier","text":"urlSession"},{"kind":"text","text":"("},{"kind":"typeIdentifier","text":"URLSession","preciseIdentifier":"c:objc(cs)NSURLSession"},{"kind":"text","text":", "},{"kind":"externalParam","text":"dataTask"},{"kind":"text","text":": "},{"kind":"typeIdentifier","text":"URLSessionDataTask","preciseIdentifier":"c:objc(cs)NSURLSessionDataTask"},{"kind":"text","text":", "},{"kind":"externalParam","text":"didReceive"},{"kind":"text","text":": "},{"kind":"typeIdentifier","text":"URLResponse","preciseIdentifier":"c:objc(cs)NSURLResponse"},{"kind":"text","text":", "},{"kind":"externalParam","text":"completionHandler"},{"kind":"text","text":": ("},{"kind":"typeIdentifier","text":"URLSession","preciseIdentifier":"c:objc(cs)NSURLSession"},{"kind":"text","text":"."},{"kind":"typeIdentifier","text":"ResponseDisposition","preciseIdentifier":"c:@E@NSURLSessionResponseDisposition"},{"kind":"text","text":") -> "},{"kind":"typeIdentifier","text":"Void","preciseIdentifier":"s:s4Voida"},{"kind":"text","text":")"}],"kind":"symbol","type":"topic"},"doc://stellar-ios-mac-sdk.stellarsdk/SQ":{"identifier":"doc:\/\/stellar-ios-mac-sdk.stellarsdk\/SQ","title":"Swift.Equatable","type":"unresolvable"},"https://html.spec.whatwg.org/multipage/server-sent-events.html":{"url":"https:\/\/html.spec.whatwg.org\/multipage\/server-sent-events.html","identifier":"https:\/\/html.spec.whatwg.org\/multipage\/server-sent-events.html","title":"W3C Server-Sent Events Specification","titleInlineContent":[{"type":"text","text":"W3C Server-Sent Events Specification"}],"type":"link"},"doc://stellar-ios-mac-sdk.stellarsdk/objc(pl)NSURLSessionDelegate":{"identifier":"doc:\/\/stellar-ios-mac-sdk.stellarsdk\/objc(pl)NSURLSessionDelegate","title":"Foundation.URLSessionDelegate","type":"unresolvable"},"doc://stellar-ios-mac-sdk.stellarsdk/documentation/stellarsdk/EventSource/addEventListener(_:handler:)":{"abstract":[{"type":"text","text":"Registers a handler for messages with a specific event type."}],"title":"addEventListener(_:handler:)","url":"\/documentation\/stellarsdk\/eventsource\/addeventlistener(_:handler:)","role":"symbol","identifier":"doc:\/\/stellar-ios-mac-sdk.stellarsdk\/documentation\/stellarsdk\/EventSource\/addEventListener(_:handler:)","fragments":[{"kind":"keyword","text":"func"},{"kind":"text","text":" "},{"kind":"identifier","text":"addEventListener"},{"kind":"text","text":"("},{"kind":"typeIdentifier","text":"String","preciseIdentifier":"s:SS"},{"kind":"text","text":", "},{"kind":"externalParam","text":"handler"},{"kind":"text","text":": (("},{"kind":"externalParam","text":"_"},{"kind":"text","text":" "},{"kind":"internalParam","text":"id"},{"kind":"text","text":": "},{"kind":"typeIdentifier","text":"String","preciseIdentifier":"s:SS"},{"kind":"text","text":"?, "},{"kind":"externalParam","text":"_"},{"kind":"text","text":" "},{"kind":"internalParam","text":"event"},{"kind":"text","text":": "},{"kind":"typeIdentifier","text":"String","preciseIdentifier":"s:SS"},{"kind":"text","text":"?, "},{"kind":"externalParam","text":"_"},{"kind":"text","text":" "},{"kind":"internalParam","text":"data"},{"kind":"text","text":": "},{"kind":"typeIdentifier","text":"String","preciseIdentifier":"s:SS"},{"kind":"text","text":"?) -> "},{"kind":"typeIdentifier","text":"Void","preciseIdentifier":"s:s4Voida"},{"kind":"text","text":"))"}],"kind":"symbol","type":"topic"},"doc://stellar-ios-mac-sdk.stellarsdk/documentation/stellarsdk/EventSource/urlSession(_:dataTask:didReceive:)":{"abstract":[],"identifier":"doc:\/\/stellar-ios-mac-sdk.stellarsdk\/documentation\/stellarsdk\/EventSource\/urlSession(_:dataTask:didReceive:)","url":"\/documentation\/stellarsdk\/eventsource\/urlsession(_:datatask:didreceive:)","fragments":[{"kind":"keyword","text":"func"},{"kind":"text","text":" "},{"kind":"identifier","text":"urlSession"},{"kind":"text","text":"("},{"kind":"typeIdentifier","preciseIdentifier":"c:objc(cs)NSURLSession","text":"URLSession"},{"kind":"text","text":", "},{"kind":"externalParam","text":"dataTask"},{"kind":"text","text":": "},{"kind":"typeIdentifier","preciseIdentifier":"c:objc(cs)NSURLSessionDataTask","text":"URLSessionDataTask"},{"kind":"text","text":", "},{"kind":"externalParam","text":"didReceive"},{"kind":"text","text":": "},{"kind":"typeIdentifier","preciseIdentifier":"s:10Foundation4DataV","text":"Data"},{"kind":"text","text":")"}],"type":"topic","title":"urlSession(_:dataTask:didReceive:)","kind":"symbol","role":"symbol"},"doc://stellar-ios-mac-sdk.stellarsdk/documentation/stellarsdk/EventSource/close()":{"type":"topic","fragments":[{"text":"func","kind":"keyword"},{"text":" ","kind":"text"},{"text":"close","kind":"identifier"},{"text":"()","kind":"text"}],"role":"symbol","abstract":[{"type":"text","text":"Closes the EventSource connection and invalidates the underlying URLSession."}],"kind":"symbol","url":"\/documentation\/stellarsdk\/eventsource\/close()","identifier":"doc:\/\/stellar-ios-mac-sdk.stellarsdk\/documentation\/stellarsdk\/EventSource\/close()","title":"close()"},"doc://stellar-ios-mac-sdk.stellarsdk/documentation/stellarsdk/EventSource/readyState":{"fragments":[{"text":"var","kind":"keyword"},{"text":" ","kind":"text"},{"text":"readyState","kind":"identifier"},{"text":": ","kind":"text"},{"text":"EventSourceState","kind":"typeIdentifier","preciseIdentifier":"s:10stellarsdk16EventSourceStateO"}],"identifier":"doc:\/\/stellar-ios-mac-sdk.stellarsdk\/documentation\/stellarsdk\/EventSource\/readyState","url":"\/documentation\/stellarsdk\/eventsource\/readystate","role":"symbol","type":"topic","kind":"symbol","title":"readyState","abstract":[{"type":"text","text":"Current connection state of the EventSource."}]},"doc://stellar-ios-mac-sdk.stellarsdk/s7CVarArgP":{"identifier":"doc:\/\/stellar-ios-mac-sdk.stellarsdk\/s7CVarArgP","title":"Swift.CVarArg","type":"unresolvable"}}}